streamlit_modal_input/__init__.py
streamlit_modal_input/frontend/build/asset-manifest.json
streamlit_modal_input/frontend/build/bootstrap.min.css
streamlit_modal_input/frontend/build/index.html
streamlit_modal_input/frontend/build/static/css/main.d3a48051.css
streamlit_modal_input/frontend/build/static/css/main.d3a48051.css.map
streamlit_modal_input/frontend/build/static/js/main.181b98b8.js
streamlit_modal_input/frontend/build/static/js/main.181b98b8.js.LICENSE.txt
streamlit_modal_input/frontend/build/static/js/main.181b98b8.js.map
streamlit_modal_input/frontend/build/static/js/main.59baeb0e.js
streamlit_modal_input/frontend/build/static/js/main.59baeb0e.js.LICENSE.txt
streamlit_modal_input/frontend/build/static/js/main.59baeb0e.js.map
streamlit_modal_input/frontend/build/static/js/main.c3778163.js
streamlit_modal_input/frontend/build/static/js/main.c3778163.js.LICENSE.txt
streamlit_modal_input/frontend/build/static/js/main.c3778163.js.map
streamlit_modal_input-0.0.13.dist-info/LICENSE
streamlit_modal_input-0.0.13.dist-info/METADATA
streamlit_modal_input-0.0.13.dist-info/WHEEL
streamlit_modal_input-0.0.13.dist-info/top_level.txt
streamlit_modal_input-0.0.13.dist-info/RECORD
