Metadata-Version: 2.1
Name: streamlit_modal_input
Version: 0.0.13
Summary: Modal text input component for Streamlit
Home-page: https://github.com/B4PT0R/streamlit_modal_input
Author: Baptiste Ferrand
Author-email: bferrand.math@gmail.com
Requires-Python: >=3.9
License-File: LICENSE
Requires-Dist: streamlit >=1.30
Requires-Dist: firebase-user
